{
  "title": "SSR과 CSR의 장단점",
  "date": "2022-01-26T00:00:00.000Z",
  "tags": [
    "Frontend"
  ],
  "draft": true,
  "summary": "SSR(Server Side Rendering)과 CSR(Client Side Rendering)의 장단점 정리해 보자",
  "body": {
    "raw": "\n# SSR과 CSR의 장단점\n\nSSR(Server Side Rendering)과 CSR(Client Side Rendering)의 장단점을 정리해 보자\n\n## SSR(Server Side Rendering)\n\n- 장점\n  - 검색 엔진 최적화 (SEO) 가능하다\n  - 초기 렌더링 속도가 빠르다\n\n- 단점\n  - 렌더링을 서버에서 하므로, 불필요한 트래핑이 낭비된다\n  - 페이지를 렌더링 할 때마다 새로 고침이 일어난다\n\n## CSR(Client Side Rendering)\n\n- 장점\n  - 새로 고침이 발생하지 않아 네이티브 앱과 유사한 사용자 경험을 제공한다\n  - 전체적인 트래픽이 감소한다\n\n- 단점\n  - 초기 렌더링 속도가 느리다.\n  - HTML 내용이 비어있어서 구글을 제외한 검색엔진 크롤러가 데이터를 수집하지 못하는 검색 엔진 최적화 (SEO) 문제가 있다\n",
    "code": "var Component=(()=>{var S=Object.create;var l=Object.defineProperty;var o=Object.getOwnPropertyDescriptor;var u=Object.getOwnPropertyNames;var R=Object.getPrototypeOf,g=Object.prototype.hasOwnProperty;var p=(i,e)=>()=>(e||i((e={exports:{}}).exports,e),e.exports),m=(i,e)=>{for(var r in e)l(i,r,{get:e[r],enumerable:!0})},s=(i,e,r,c)=>{if(e&&typeof e==\"object\"||typeof e==\"function\")for(let d of u(e))!g.call(i,d)&&d!==r&&l(i,d,{get:()=>e[d],enumerable:!(c=o(e,d))||c.enumerable});return i};var x=(i,e,r)=>(r=i!=null?S(R(i)):{},s(e||!i||!i.__esModule?l(r,\"default\",{value:i,enumerable:!0}):r,i)),C=i=>s(l({},\"__esModule\",{value:!0}),i);var h=p((M,t)=>{t.exports=_jsx_runtime});var b={};m(b,{default:()=>_,frontmatter:()=>f});var n=x(h()),f={title:\"SSR\\uACFC CSR\\uC758 \\uC7A5\\uB2E8\\uC810\",date:\"2022-01-26\",tags:[\"Frontend\"],draft:!0,summary:\"SSR(Server Side Rendering)\\uACFC CSR(Client Side Rendering)\\uC758 \\uC7A5\\uB2E8\\uC810 \\uC815\\uB9AC\\uD574 \\uBCF4\\uC790\"};function a(i){let e=Object.assign({h1:\"h1\",a:\"a\",span:\"span\",p:\"p\",h2:\"h2\",ul:\"ul\",li:\"li\"},i.components);return(0,n.jsxs)(n.Fragment,{children:[(0,n.jsxs)(e.h1,{id:\"ssr\\uACFC-csr\\uC758-\\uC7A5\\uB2E8\\uC810\",children:[(0,n.jsx)(e.a,{\"aria-hidden\":\"true\",href:\"#ssr\\uACFC-csr\\uC758-\\uC7A5\\uB2E8\\uC810\",tabIndex:\"-1\",children:(0,n.jsx)(e.span,{className:\"icon icon-link\"})}),\"SSR\\uACFC CSR\\uC758 \\uC7A5\\uB2E8\\uC810\"]}),(0,n.jsx)(e.p,{children:\"SSR(Server Side Rendering)\\uACFC CSR(Client Side Rendering)\\uC758 \\uC7A5\\uB2E8\\uC810\\uC744 \\uC815\\uB9AC\\uD574 \\uBCF4\\uC790\"}),(0,n.jsxs)(e.h2,{id:\"ssrserver-side-rendering\",children:[(0,n.jsx)(e.a,{\"aria-hidden\":\"true\",href:\"#ssrserver-side-rendering\",tabIndex:\"-1\",children:(0,n.jsx)(e.span,{className:\"icon icon-link\"})}),\"SSR(Server Side Rendering)\"]}),(0,n.jsxs)(e.ul,{children:[(0,n.jsxs)(e.li,{children:[(0,n.jsx)(e.p,{children:\"\\uC7A5\\uC810\"}),(0,n.jsxs)(e.ul,{children:[(0,n.jsx)(e.li,{children:\"\\uAC80\\uC0C9 \\uC5D4\\uC9C4 \\uCD5C\\uC801\\uD654 (SEO) \\uAC00\\uB2A5\\uD558\\uB2E4\"}),(0,n.jsx)(e.li,{children:\"\\uCD08\\uAE30 \\uB80C\\uB354\\uB9C1 \\uC18D\\uB3C4\\uAC00 \\uBE60\\uB974\\uB2E4\"})]})]}),(0,n.jsxs)(e.li,{children:[(0,n.jsx)(e.p,{children:\"\\uB2E8\\uC810\"}),(0,n.jsxs)(e.ul,{children:[(0,n.jsx)(e.li,{children:\"\\uB80C\\uB354\\uB9C1\\uC744 \\uC11C\\uBC84\\uC5D0\\uC11C \\uD558\\uBBC0\\uB85C, \\uBD88\\uD544\\uC694\\uD55C \\uD2B8\\uB798\\uD551\\uC774 \\uB0AD\\uBE44\\uB41C\\uB2E4\"}),(0,n.jsx)(e.li,{children:\"\\uD398\\uC774\\uC9C0\\uB97C \\uB80C\\uB354\\uB9C1 \\uD560 \\uB54C\\uB9C8\\uB2E4 \\uC0C8\\uB85C \\uACE0\\uCE68\\uC774 \\uC77C\\uC5B4\\uB09C\\uB2E4\"})]})]})]}),(0,n.jsxs)(e.h2,{id:\"csrclient-side-rendering\",children:[(0,n.jsx)(e.a,{\"aria-hidden\":\"true\",href:\"#csrclient-side-rendering\",tabIndex:\"-1\",children:(0,n.jsx)(e.span,{className:\"icon icon-link\"})}),\"CSR(Client Side Rendering)\"]}),(0,n.jsxs)(e.ul,{children:[(0,n.jsxs)(e.li,{children:[(0,n.jsx)(e.p,{children:\"\\uC7A5\\uC810\"}),(0,n.jsxs)(e.ul,{children:[(0,n.jsx)(e.li,{children:\"\\uC0C8\\uB85C \\uACE0\\uCE68\\uC774 \\uBC1C\\uC0DD\\uD558\\uC9C0 \\uC54A\\uC544 \\uB124\\uC774\\uD2F0\\uBE0C \\uC571\\uACFC \\uC720\\uC0AC\\uD55C \\uC0AC\\uC6A9\\uC790 \\uACBD\\uD5D8\\uC744 \\uC81C\\uACF5\\uD55C\\uB2E4\"}),(0,n.jsx)(e.li,{children:\"\\uC804\\uCCB4\\uC801\\uC778 \\uD2B8\\uB798\\uD53D\\uC774 \\uAC10\\uC18C\\uD55C\\uB2E4\"})]})]}),(0,n.jsxs)(e.li,{children:[(0,n.jsx)(e.p,{children:\"\\uB2E8\\uC810\"}),(0,n.jsxs)(e.ul,{children:[(0,n.jsx)(e.li,{children:\"\\uCD08\\uAE30 \\uB80C\\uB354\\uB9C1 \\uC18D\\uB3C4\\uAC00 \\uB290\\uB9AC\\uB2E4.\"}),(0,n.jsx)(e.li,{children:\"HTML \\uB0B4\\uC6A9\\uC774 \\uBE44\\uC5B4\\uC788\\uC5B4\\uC11C \\uAD6C\\uAE00\\uC744 \\uC81C\\uC678\\uD55C \\uAC80\\uC0C9\\uC5D4\\uC9C4 \\uD06C\\uB864\\uB7EC\\uAC00 \\uB370\\uC774\\uD130\\uB97C \\uC218\\uC9D1\\uD558\\uC9C0 \\uBABB\\uD558\\uB294 \\uAC80\\uC0C9 \\uC5D4\\uC9C4 \\uCD5C\\uC801\\uD654 (SEO) \\uBB38\\uC81C\\uAC00 \\uC788\\uB2E4\"})]})]})]})]})}function j(i={}){let{wrapper:e}=i.components||{};return e?(0,n.jsx)(e,Object.assign({},i,{children:(0,n.jsx)(a,i)})):a(i)}var _=j;return C(b);})();\n;return Component;"
  },
  "_id": "blog/2022/01/26/pros-and-cons-of-ssr-and-csr.mdx",
  "_raw": {
    "sourceFilePath": "blog/2022/01/26/pros-and-cons-of-ssr-and-csr.mdx",
    "sourceFileName": "pros-and-cons-of-ssr-and-csr.mdx",
    "sourceFileDir": "blog/2022/01/26",
    "contentType": "mdx",
    "flattenedPath": "blog/2022/01/26/pros-and-cons-of-ssr-and-csr"
  },
  "type": "Blog",
  "readingTime": {
    "text": "2 min read",
    "minutes": 1.035,
    "time": 62100,
    "words": 207
  },
  "slug": "2022/01/26/pros-and-cons-of-ssr-and-csr",
  "path": "blog/2022/01/26/pros-and-cons-of-ssr-and-csr",
  "filePath": "blog/2022/01/26/pros-and-cons-of-ssr-and-csr.mdx",
  "toc": [
    {
      "value": "SSR과 CSR의 장단점",
      "url": "#ssr과-csr의-장단점",
      "depth": 1
    },
    {
      "value": "SSR(Server Side Rendering)",
      "url": "#ssrserver-side-rendering",
      "depth": 2
    },
    {
      "value": "CSR(Client Side Rendering)",
      "url": "#csrclient-side-rendering",
      "depth": 2
    }
  ]
}